<?xml version="1.0" encoding="UTF-8"?>
<mapping xmlns="http://castor.exolab.org/" xmlns:cst="http://castor.exolab.org/">
	<description xmlns="">Castor generated mapping file
	</description>
	<class name="com.cio.castor.Contacts">
		<description xmlns="">Default mapping for class
			com.cio.castor.Contacts
		</description>
		<map-to xml="contacts" />
		<field name="contact" type="java.lang.Object" collection="set">
			<bind-xml name="contact" node="element" />
		</field>
	</class>

	<description xmlns="">Castor generated mapping file
	</description>
	<class name="com.cio.castor.Contact">
		<description xmlns="">Default mapping for class
			com.cio.castor.Contact
		</description>
		<map-to xml="contact" />
		<field name="numbers" type="java.lang.Object" collection="set">
			<bind-xml name="numbers" node="element" />
		</field>
		<field name="name" type="java.lang.String">
			<bind-xml name="name" node="element" />
		</field>
	</class>
</mapping>